ktrader/__init__.py
ktrader/candle_trader/__init__.py
ktrader/candle_trader/candle_trader.py
ktrader/candle_trader/component/__init__.py
ktrader/candle_trader/component/analysis.py
ktrader/candle_trader/component/order.py
ktrader/candle_trader/component/period.py
ktrader/candle_trader/component/record.py
ktrader/candle_trader/component/rule.py
ktrader/candle_trader/component/trade.py
ktrader/strategy/__init__.py
ktrader/strategy/dual_thrust.py
ktrader/utils/__init__.py
ktrader/utils/candle.py
ktrader/utils/date.py
ktrader/utils/price.py
ktrader-1.0.11.dist-info/METADATA
ktrader-1.0.11.dist-info/WHEEL
ktrader-1.0.11.dist-info/top_level.txt
ktrader-1.0.11.dist-info/RECORD
